leectf/__init__.py
leectf/algo/__init__.py
leectf/algo/algo.py
leectf/algo/hilbert.py
leectf/helpers/__init__.py
leectf/helpers/listhelper.py
leectf/plot/__init__.py
leectf/plot/plot.py
leectf/plot/scatterPlot.py
leectf/verify/__init__.py
leectf-1.1.0.dist-info/LICENSE.txt
leectf-1.1.0.dist-info/METADATA
leectf-1.1.0.dist-info/WHEEL
leectf-1.1.0.dist-info/top_level.txt
leectf-1.1.0.dist-info/RECORD
