Metadata-Version: 2.1
Name: leectf
Version: 1.1.0
Summary: A small package to improve the efficiency and productivity of CTF and Attack
Home-page: https://leeyabug.top
Author: leeya_bug
Author-email: leeyang928320@gmail.com
Classifier: Programming Language :: Python :: 3
Classifier: License :: OSI Approved :: MIT License
Classifier: Operating System :: OS Independent
Requires-Python: >=3.6
License-File: LICENSE.txt
